ibats_huobi_feeder/__init__.py
ibats_huobi_feeder/config.py
ibats_huobi_feeder/backend/__init__.py
ibats_huobi_feeder/backend/check.py
ibats_huobi_feeder/backend/handler.py
ibats_huobi_feeder/backend/immigration.py
ibats_huobi_feeder/backend/orm.py
ibats_huobi_feeder/feed/__init__.py
ibats_huobi_feeder/feed/md_feeder.py
ibats_huobi_feeder/test/__init__.py
ibats_huobi_feeder/test/bulk_pattern.py
ibats_huobi_feeder/test/md.py
IBATS_Huobi_Feeder-0.1.3.dist-info/LICENSE
IBATS_Huobi_Feeder-0.1.3.dist-info/METADATA
IBATS_Huobi_Feeder-0.1.3.dist-info/WHEEL
IBATS_Huobi_Feeder-0.1.3.dist-info/top_level.txt
IBATS_Huobi_Feeder-0.1.3.dist-info/RECORD
