Metadata-Version: 2.1
Name: IBATS-Huobi-Feeder
Version: 0.1.3
Summary: 连接 Huobi 火币交易所，获取实时行情、历史行情，保存到mysql数据库同时redis广播，供 IBATS 交易平台进行策略回测、分析，交易使用
Home-page: https://github.com/IBATS/IBATS_HuobiFeeder
Author: MG
Author-email: mmmaaaggg@163.com
License: UNKNOWN
Platform: UNKNOWN
Classifier: Programming Language :: Python :: 3 :: Only
Classifier: Programming Language :: Python :: 3.6
Classifier: Programming Language :: Python :: 3.7
Classifier: Operating System :: Microsoft :: Windows
Classifier: Operating System :: Unix
Classifier: Operating System :: POSIX
Classifier: License :: OSI Approved :: MIT License
Classifier: Development Status :: 5 - Production/Stable
Classifier: Environment :: No Input/Output (Daemon)
Classifier: Intended Audience :: Developers
Classifier: Natural Language :: Chinese (Simplified)
Classifier: Topic :: Software Development
Requires-Python: >=3.6
Requires-Dist: IBATS-Common
Requires-Dist: huobitrade (==0.1.9)
Requires-Dist: websocket-client (>=0.46.0)
Requires-Dist: mysqlclient (>=1.3.8)
Requires-Dist: prodconpattern (==0.1.1)
